[
  {
    "50.00 percentile latency (ns)": 37053126,
    "90.00 percentile latency (ns)": 49009786,
    "95.00 percentile latency (ns)": 53089435,
    "97.00 percentile latency (ns)": 56190822,
    "99.00 percentile latency (ns)": 69406770,
    "99.90 percentile latency (ns)": 43945166581,
    "Completed samples per second": 5395.67,
    "Max latency (ns)": 60191090776,
    "Mean latency (ns)": 214405129,
    "Min duration satisfied": "Yes",
    "Min latency (ns)": 9015959,
    "Min queries satisfied": "Yes",
    "Mode": "Performance",
    "Performance constraints satisfied": "Yes",
    "Result is": "VALID",
    "SUT name": "BERT SERVER",
    "Scenario": "server",
    "Scheduled samples per second": 5401.69,
    "accelerator_frequency": "585 MHz",
    "accelerator_host_interconnect": "PCIe 3.0 x16",
    "accelerator_interconnect": "",
    "accelerator_interconnect_topology": "",
    "accelerator_memory_capacity": "16 GB",
    "accelerator_memory_configuration": "GDDR6",
    "accelerator_model_name": "NVIDIA Tesla T4",
    "accelerator_on-chip_memories": "L1: 40x 64KB, L2: 4MB per chip",
    "accelerators_per_node": 16,
    "accuracy_log_probability": 0,
    "accuracy_log_rng_seed": 0,
    "accuracy_log_sampling_target": 0,
    "characteristics.scheduled_queries_per_second": 5401.69,
    "characteristics.scheduled_queries_per_second.normalized_per_core": 337.605625,
    "characteristics.scheduled_queries_per_second.normalized_per_processor": 337.605625,
    "ck_system": "GIGABYTE_G292-Z43_16xT4",
    "ck_used": false,
    "cooling": "Air-cooled",
    "dataset": "SQuAD v1.1",
    "dataset_link": "",
    "dim_x_default": "seq_number",
    "dim_y_default": "characteristics.scheduled_queries_per_second",
    "dim_y_maximize": false,
    "division": "closed",
    "formal_model": "bert",
    "formal_model_accuracy": 99.0,
    "formal_model_link": "",
    "framework": "TensorRT 7.2, CUDA 11.0 Update 1",
    "host_memory_capacity": "1024 GB",
    "host_memory_configuration": "",
    "host_networking": "",
    "host_networking_topology": "",
    "host_processor_caches": "L3 cache 256MB",
    "host_processor_core_count": 64,
    "host_processor_frequency": "2.25 GHz",
    "host_processor_interconnect": "1x 16-20GT/s xGMI2",
    "host_processor_model_name": "AMD EPYC 7742",
    "host_processors_per_node": 2,
    "host_storage_capacity": "1.92 TB",
    "host_storage_type": "SSD",
    "hw_notes": "ECC off",
    "informal_model": "bert-99",
    "input_data_types": "int32",
    "max_async_queries": 0,
    "max_duration (ms)": 0,
    "max_query_count": 0,
    "min_duration (ms)": 60000,
    "min_query_count": 270336,
    "mlperf_version": "v0.7",
    "normalize_cores": 16,
    "normalize_processors": 16,
    "note_code": "https://github.com/mlcommons/inference_results_v0.7/tree/master/closed/Gigabyte/code",
    "note_details": "https://github.com/mlcommons/inference_results_v0.7/tree/master/closed/Gigabyte/results/GIGABYTE_G292-Z43_16xT4",
    "number_of_nodes": 1,
    "operating_system": "Ubuntu 18.04.4",
    "other_software_stack": "TensorRT 7.2, CUDA 11.0 Update 1, cuDNN 8.0.2, DALI 0.25.0",
    "performance_issue_same": true,
    "performance_issue_same_index": 0,
    "performance_issue_unique": true,
    "performance_sample_count": 10833,
    "print_timestamps": true,
    "problem": false,
    "qsl_rng_seed": 12786827339337101903,
    "retraining": "N",
    "sample_index_rng_seed": 12640797754436136668,
    "samples_per_query": 1,
    "schedule_rng_seed": 3135815929913719677,
    "starting_weights_filename": "bert_large_v1_1_fake_quant.onnx",
    "status": "preview",
    "submitter": "GIGABYTE",
    "submitter_link": "https://github.com/ctuning/ck-mlperf-inference/tree/main/bench.mlperf.submitter/Gigabyte",
    "sw_notes": "",
    "system_link": "https://github.com/ctuning/ck-mlperf-inference/tree/main/bench.mlperf.system/GIGABYTE_G292-Z43_16xT4",
    "system_name": "GIGABYTE G292-Z43 16xT4",
    "system_type": "datacenter",
    "target_latency (ns)": 130000000,
    "target_qps": 5400,
    "task": "NLP",
    "task2": "nlp",
    "total_cores": 128,
    "uid": "20902045a79d3663",
    "use_accelerator": true,
    "weight_data_types": "int8,fp16",
    "weight_transformations": "quantization, affine fusion"
  },
  {
    "50.00 percentile latency (ns)": 7589466,
    "90.00 percentile latency (ns)": 9986698,
    "95.00 percentile latency (ns)": 10673586,
    "97.00 percentile latency (ns)": 11190421,
    "99.00 percentile latency (ns)": 12607229,
    "99.90 percentile latency (ns)": 20837819,
    "Completed samples per second": 1418.67,
    "Max latency (ns)": 66469227,
    "Mean latency (ns)": 8000205,
    "Min duration satisfied": "Yes",
    "Min latency (ns)": 5989096,
    "Min queries satisfied": "Yes",
    "Mode": "Performance",
    "Performance constraints satisfied": "Yes",
    "Result is": "VALID",
    "SUT name": "BERT SERVER",
    "Scenario": "server",
    "Scheduled samples per second": 1418.73,
    "accelerator_frequency": "585 MHz",
    "accelerator_host_interconnect": "PCIe 3.0 x16",
    "accelerator_interconnect": "",
    "accelerator_interconnect_topology": "",
    "accelerator_memory_capacity": "16 GB",
    "accelerator_memory_configuration": "GDDR6",
    "accelerator_model_name": "NVIDIA Tesla T4",
    "accelerator_on-chip_memories": "L1: 40x 64KB, L2: 4MB per chip",
    "accelerators_per_node": 16,
    "accuracy_log_probability": 0,
    "accuracy_log_rng_seed": 0,
    "accuracy_log_sampling_target": 0,
    "characteristics.scheduled_queries_per_second": 1418.73,
    "characteristics.scheduled_queries_per_second.normalized_per_core": 88.670625,
    "characteristics.scheduled_queries_per_second.normalized_per_processor": 88.670625,
    "ck_system": "GIGABYTE_G292-Z43_16xT4",
    "ck_used": false,
    "cooling": "Air-cooled",
    "dataset": "SQuAD v1.1",
    "dataset_link": "",
    "dim_x_default": "seq_number",
    "dim_y_default": "characteristics.scheduled_queries_per_second",
    "dim_y_maximize": false,
    "division": "closed",
    "formal_model": "bert",
    "formal_model_accuracy": 99.9,
    "formal_model_link": "",
    "framework": "TensorRT 7.2, CUDA 11.0 Update 1",
    "host_memory_capacity": "1024 GB",
    "host_memory_configuration": "",
    "host_networking": "",
    "host_networking_topology": "",
    "host_processor_caches": "L3 cache 256MB",
    "host_processor_core_count": 64,
    "host_processor_frequency": "2.25 GHz",
    "host_processor_interconnect": "1x 16-20GT/s xGMI2",
    "host_processor_model_name": "AMD EPYC 7742",
    "host_processors_per_node": 2,
    "host_storage_capacity": "1.92 TB",
    "host_storage_type": "SSD",
    "hw_notes": "ECC off",
    "informal_model": "bert-99.9",
    "input_data_types": "int32",
    "max_async_queries": 0,
    "max_duration (ms)": 0,
    "max_query_count": 0,
    "min_duration (ms)": 60000,
    "min_query_count": 270336,
    "mlperf_version": "v0.7",
    "normalize_cores": 16,
    "normalize_processors": 16,
    "note_code": "https://github.com/mlcommons/inference_results_v0.7/tree/master/closed/Gigabyte/code",
    "note_details": "https://github.com/mlcommons/inference_results_v0.7/tree/master/closed/Gigabyte/results/GIGABYTE_G292-Z43_16xT4",
    "number_of_nodes": 1,
    "operating_system": "Ubuntu 18.04.4",
    "other_software_stack": "TensorRT 7.2, CUDA 11.0 Update 1, cuDNN 8.0.2, DALI 0.25.0",
    "performance_issue_same": true,
    "performance_issue_same_index": 0,
    "performance_issue_unique": true,
    "performance_sample_count": 10833,
    "print_timestamps": true,
    "problem": false,
    "qsl_rng_seed": 12786827339337101903,
    "retraining": "N",
    "sample_index_rng_seed": 12640797754436136668,
    "samples_per_query": 1,
    "schedule_rng_seed": 3135815929913719677,
    "starting_weights_filename": "bert_large_v1_1_fake_quant.onnx",
    "status": "preview",
    "submitter": "GIGABYTE",
    "submitter_link": "https://github.com/ctuning/ck-mlperf-inference/tree/main/bench.mlperf.submitter/Gigabyte",
    "sw_notes": "",
    "system_link": "https://github.com/ctuning/ck-mlperf-inference/tree/main/bench.mlperf.system/GIGABYTE_G292-Z43_16xT4",
    "system_name": "GIGABYTE G292-Z43 16xT4",
    "system_type": "datacenter",
    "target_latency (ns)": 130000000,
    "target_qps": 1420,
    "task": "NLP",
    "task2": "nlp",
    "total_cores": 128,
    "uid": "458b90cf8a953e63",
    "use_accelerator": true,
    "weight_data_types": "int8,fp16",
    "weight_transformations": "quantization, affine fusion"
  }
]
